asfyaml/__init__.py
asfyaml/asfyaml.py
asfyaml/cli.py
asfyaml/dataobjects.py
asfyaml/envvars.py
asfyaml/feature/__init__.py
asfyaml/feature/github/__init__.py
asfyaml/feature/github/autolink.py
asfyaml/feature/github/branch_protection.py
asfyaml/feature/github/collaborators.py
asfyaml/feature/github/constants.py
asfyaml/feature/github/custom_subjects.py
asfyaml/feature/github/features.py
asfyaml/feature/github/housekeeping.py
asfyaml/feature/github/merge_buttons.py
asfyaml/feature/github/metadata.py
asfyaml/feature/github/pages.py
asfyaml/feature/github/protected_tags.py
asfyaml/feature/jekyll.py
asfyaml/feature/notifications.py
asfyaml/feature/pelican.py
asfyaml/feature/testfeature.py
asfyaml/feature/website_publish.py
asfyaml/feature/website_staging.py
asfyaml/mappings.py
asfyaml/validators.py
asfyaml-0.1.0.dist-info/LICENSE
asfyaml-0.1.0.dist-info/LICENSE-template.txt
asfyaml-0.1.0.dist-info/METADATA
asfyaml-0.1.0.dist-info/WHEEL
asfyaml-0.1.0.dist-info/entry_points.txt
asfyaml-0.1.0.dist-info/RECORD
