Metadata-Version: 2.1
Name: asfyaml
Version: 0.1.0
Summary: 
Author: Daniel Gruno
Author-email: humbedooh@apache.org
Requires-Python: >=3.10
Classifier: Programming Language :: Python :: 3
Classifier: Programming Language :: Python :: 3.10
Classifier: Programming Language :: Python :: 3.11
Classifier: Programming Language :: Python :: 3.12
Requires-Dist: PyGithub (>=2.5.0,<3.0.0)
Requires-Dist: asfpy
Requires-Dist: easydict
Requires-Dist: pyyaml
Requires-Dist: requests
Requires-Dist: strictyaml
